Workbook

Sheet Dashboard Ringkasan
A1: REKAPITULASI TRANSAKSI REKENING KORAN BNI
A2: PT HIJAU SEJAHTERA BERSAMA | Rekening Giro No: 692291557 | Periode: 01 Jan 2026 - 31 Jul 2026
A4: Informasi Perusahaan & Rekening | F4: SALDO AWAL (01 JAN 2026) | G4: TOTAL PEMASUKAN (KREDIT) | H4: TOTAL PENGELUARAN (DEBET) | I4: NET CASH FLOW | J4: SALDO AKHIR (31 JUL 2026)
A5: Nama Perusahaan | B5: PT HIJAU SEJAHTERA BERSAMA | F5: 2316102 | G5: =SUM(E12:E18) -> 2368658312 | H5: =SUM(D12:D18) -> 2238150351 | I5: =G5-H5 -> 130507961 | J5: 132824063
A6: Nomor Rekening | B6: 692291557
A7: Mata Uang / Tipe | B7: IDR / CURRENT (Giro BNI)
A8: Alamat Perusahaan | B8: DUSUN I PUJOSARI RT 001 RW 001
A9: Periode Transaksi | B9: 01 Januari 2026 - 31 Juli 2026 (7 Bulan)
A10: Ringkasan Mutasi Per Bulan (Jan - Jul 2026)
A11: No | B11: Bulan | C11: Saldo Awal (Rp) | D11: Total Debet / Keluar (Rp) | E11: Total Kredit / Masuk (Rp) | F11: Net Flow (Rp) | G11: Saldo Akhir (Rp) | H11: Jumlah Transaksi
A12: 1 | B12: Jan 2026 | C12: 2316102 | D12: 27174981 | E12: 28500010 | F12: =E12-D12 -> 1325029 | G12: 3641131 | H12: 18
A13: 2 | B13: Feb 2026 | C13: 3641131 | D13: 34532589 | E13: 32050296 | F13: =E13-D13 -> -2482293 | G13: 1158838 | H13: 12
A14: 3 | B14: Mar 2026 | C14: 1158838 | D14: 8115149 | E14: 142069630 | F14: =E14-D14 -> 133954481 | G14: 135113319 | H14: 9
A15: 4 | B15: Apr 2026 | C15: 135113319 | D15: 646720434 | E15: 554778538 | F15: =E15-D15 -> -91941896 | G15: 43171423 | H15: 23
A16: 5 | B16: Mei 2026 | C16: 43171423 | D16: 551530582 | E16: 514791752 | F16: =E16-D16 -> -36738830 | G16: 6432593 | H16: 22
A17: 6 | B17: Jun 2026 | C17: 6432593 | D17: 685260678 | E17: 803248487 | F17: =E17-D17 -> 117987809 | G17: 124420402 | H17: 32
A18: 7 | B18: Jul 2026 | C18: 124420402 | D18: 284815938 | E18: 293219599 | F18: =E18-D18 -> 8403661 | G18: 132824063 | H18: 13
B19: TOTAL / SALDO | C19: 2316102 | D19: =SUM(D12:D18) -> 2238150351 | E19: =SUM(E12:E18) -> 2368658312 | F19: =E19-D19 -> 130507961 | G19: 132824063 | H19: =SUM(H12:H18) -> 129
A22: Breakdown Transaksi Berdasarkan Kategori Pengeluaran & Pemasukan
A23: No | B23: Kategori Transaksi | C23: Jumlah Transaksi | D23: Total Debet / Pengeluaran (Rp) | E23: Total Kredit / Pemasukan (Rp) | F23: Net Impact (Rp)
A24: 1 | B24: Transfer / Pemindahan | C24: =COUNTIF('Rekap Master'!H:H, B24) -> 31 | D24: =SUMIF('Rekap Master'!H:H, B24, 'Rekap Master'!J:J) -> 957402250 | E24: =SUMIF('Rekap Master'!H:H, B24, 'Rekap Master'!K:K) -> 313870858 | F24: =E24-D24 -> -643531392
A25: 2 | B25: Pajak (MPN G2) | C25: =COUNTIF('Rekap Master'!H:H, B25) -> 27 | D25: =SUMIF('Rekap Master'!H:H, B25, 'Rekap Master'!J:J) -> 1099298647 | E25: =SUMIF('Rekap Master'!H:H, B25, 'Rekap Master'!K:K) -> 0 | F25: =E25-D25 -> -1099298647
A26: 3 | B26: BPJS Kesehatan | C26: =COUNTIF('Rekap Master'!H:H, B26) -> 4 | D26: =SUMIF('Rekap Master'!H:H, B26, 'Rekap Master'!J:J) -> 18626910 | E26: =SUMIF('Rekap Master'!H:H, B26, 'Rekap Master'!K:K) -> 0 | F26: =E26-D26 -> -18626910
A27: 4 | B27: BPJS Ketenagakerjaan | C27: =COUNTIF('Rekap Master'!H:H, B27) -> 6 | D27: =SUMIF('Rekap Master'!H:H, B27, 'Rekap Master'!J:J) -> 9496801 | E27: =SUMIF('Rekap Master'!H:H, B27, 'Rekap Master'!K:K) -> 0 | F27: =E27-D27 -> -9496801
A28: 5 | B28: Listrik / PLN | C28: =COUNTIF('Rekap Master'!H:H, B28) -> 6 | D28: =SUMIF('Rekap Master'!H:H, B28, 'Rekap Master'!J:J) -> 3010500 | E28: =SUMIF('Rekap Master'!H:H, B28, 'Rekap Master'!K:K) -> 0 | F28: =E28-D28 -> -3010500
A29: 6 | B29: Transfer BI-FAST | C29: =COUNTIF('Rekap Master'!H:H, B29) -> 30 | D29: =SUMIF('Rekap Master'!H:H, B29, 'Rekap Master'!J:J) -> 35000 | E29: =SUMIF('Rekap Master'!H:H, B29, 'Rekap Master'!K:K) -> 1586874280 | F29: =E29-D29 -> 1586839280
A30: 7 | B30: Setor Tunai | C30: =COUNTIF('Rekap Master'!H:H, B30) -> 1 | D30: =SUMIF('Rekap Master'!H:H, B30, 'Rekap Master'!J:J) -> 0 | E30: =SUMIF('Rekap Master'!H:H, B30, 'Rekap Master'!K:K) -> 132500000 | F30: =E30-D30 -> 132500000
A31: 8 | B31: Jasa Giro | C31: =COUNTIF('Rekap Master'!H:H, B31) -> 7 | D31: =SUMIF('Rekap Master'!H:H, B31, 'Rekap Master'!J:J) -> 0 | E31: =SUMIF('Rekap Master'!H:H, B31, 'Rekap Master'!K:K) -> 494013 | F31: =E31-D31 -> 494013
A32: 9 | B32: Biaya Admin / Bank | C32: =COUNTIF('Rekap Master'!H:H, B32) -> 8 | D32: =SUMIF('Rekap Master'!H:H, B32, 'Rekap Master'!J:J) -> 181500 | E32: =SUMIF('Rekap Master'!H:H, B32, 'Rekap Master'!K:K) -> 0 | F32: =E32-D32 -> -181500
A33: 10 | B33: Pajak PPh | C33: =COUNTIF('Rekap Master'!H:H, B33) -> 5 | D33: =SUMIF('Rekap Master'!H:H, B33, 'Rekap Master'!J:J) -> 98743 | E33: =SUMIF('Rekap Master'!H:H, B33, 'Rekap Master'!K:K) -> 0 | F33: =E33-D33 -> -98743
A34: 11 | B34: Lainnya | C34: =COUNTIF('Rekap Master'!H:H, B34) -> 4 | D34: =SUMIF('Rekap Master'!H:H, B34, 'Rekap Master'!J:J) -> 150000000 | E34: =SUMIF('Rekap Master'!H:H, B34, 'Rekap Master'!K:K) -> 334919161 | F34: =E34-D34 -> 184919161
B35: TOTAL KATEGORI | C35: =SUM(C24:C34) -> 129 | D35: =SUM(D24:D34) -> 2238150351 | E35: =SUM(E24:E34) -> 2368658312 | F35: =E35-D35 -> 130507961

Sheet Rekap Master
A1: DAFTAR MASTER TRANSAKSI REKENING KORAN BNI (JANUARI - JULI 2026)
A2: PT HIJAU SEJAHTERA BERSAMA | Total Transaksi: 129 Records
A4: No | B4: Bulan | C4: Posting Date | D4: Effective Date | E4: No. Jurnal | F4: Cabang / Branch | G4: Uraian / Deskripsi Transaksi | H4: Kategori | I4: DB/CR | J4: Debet / Keluar (Rp) | K4: Kredit / Masuk (Rp) | L4: Saldo Akhir (Rp)
A5: 1 | B5: Jan 2026 | C5: 09/01/2026 11.26.40 | D5: 09/01/2026 11.26.40 | E5: 905653 | F5: INTERNET BANKING | G5: TRF/PAY/TOP-UP ECHANNEL | PEMINDAHAN DARI 1140010073537 | 0000000000000000 | WIJI INDRAYANI Lainnya | H5: Transfer / Pemindahan | I5: K | J5: 0 | K5: 5500000 | L5: 7816102
A6: 2 | B6: Jan 2026 | C6: 09/01/2026 11.35.14 | D6: 09/01/2026 11.35.14 | E6: 211467 | F6: DIVISI TRANSACTI ONAL BANKING SERVICES (TBS) | G6: TRANSFER KE | BILL PAYMENT (MPN G2 IDR ) NO :041659442003798 | H6: Pajak (MPN G2) | I6: D | J6: 13240 | K6: 0 | L6: 7802862
A7: 3 | B7: Jan 2026 | C7: 09/01/2026 11.35.14 | D7: 09/01/2026 11.35.14 | E7: 201348 | F7: DIVISI TRANSACTI ONAL BANKING SERVICES (TBS) | G7: TRANSFER KE | 8888890001020743 67DBD5B548FB84C4 | BILL PAYMENT (H2H BPJS KES) NO :67DBD5B548FB84C4 | H7: BPJS Kesehatan | I7: D | J7: 3804623 | K7: 0 | L7: 3998239
A8: 4 | B8: Jan 2026 | C8: 09/01/2026 11.35.15 | D8: 09/01/2026 11.35.15 | E8: 212011 | F8: INTERNAL | G8: TRF/PAY/TOP-UP ECHANNEL | PEMINDAHAN KE 13001017205539 | 6010047890623568 | BNI DIRECT | H8: Transfer / Pemindahan | I8: D | J8: 540000 | K8: 0 | L8: 3458239
A9: 5 | B9: Jan 2026 | C9: 09/01/2026 00.00.00 | D9: 09/01/2026 00.00.00 | E9: 212011 | F9: INTERNAL DIVISI | G9: BY TRX ATM PRIMA | H9: Biaya Admin / Bank | I9: D | J9: 6500 | K9: 0 | L9: 3451739
A10: 6 | B10: Jan 2026 | C10: 09/01/2026 11.35.16 | D10: 09/01/2026 11.35.16 | E10: 201906 | F10: TRANSACTI ONAL BANKING SERVICES (TBS) | G10: TRANSFER KE | BILL PAYMENT (H2H BPJS TK ) NO :418307362000 | H10: BPJS Ketenagakerjaan | I10: D | J10: 1250475 | K10: 0 | L10: 2201264
A11: 7 | B11: Jan 2026 | C11: 14/01/2026 10.18.57 | D11: 14/01/2026 10.18.57 | E11: 936510 | F11: INTERNET BANKING | G11: TRF/PAY/TOP-UP ECHANNEL | PEMINDAHAN DARI 1140016063946 | 0000000000000000 | HIJAU SEJAHTERA BERS BI FAST Transfer | H11: Transfer BI-FAST | I11: K | J11: 0 | K11: 23000000 | L11: 25201264
A12: 8 | B12: Jan 2026 | C12: 14/01/2026 13.43.32 | D12: 14/01/2026 13.43.32 | E12: 342099 | F12: DIVISI TRANSACTI ONAL BANKING SERVICES (TBS) | G12: TRANSFER KE | BILL PAYMENT (MPN G2 IDR ) NO :030810890597019 | H12: Pajak (MPN G2) | I12: D | J12: 16429563 | K12: 0 | L12: 8771701
A13: 9 | B13: Jan 2026 | C13: 14/01/2026 13.43.31 | D13: 14/01/2026 13.43.31 | E13: 968792 | F13: DIVISI TRANSACTI ONAL BANKING SERVICES (TBS) | G13: TRF/PAY/TOP-UP ECHANNEL | 6010043330000011 | BNI DIRECT | BILL PAYMENT (PLN PREPAID ) NO :45039450379 | H13: Listrik / PLN | I13: D | J13: 1000000 | K13: 0 | L13: 7771701
A14: 10 | B14: Jan 2026 | C14: 14/01/2026 13.43.31 | D14: 14/01/2026 13.43.31 | E14: 968792 | F14: DIVISI TRANSACTI ONAL BANKING SERVICES (TBS) | G14: TRF/PAY/TOP-UP ECHANNEL | 6010043330000011 | BNI DIRECT | BIAYA ADMIN (PLN PREPAID ) NO :45039450379 4505 | H14: Listrik / PLN | I14: D | J14: 3500 | K14: 0 | L14: 7768201
A15: 11 | B15: Jan 2026 | C15: 14/01/2026 13.43.32 | D15: 14/01/2026 13.43.32 | E15: 967925 | F15: DIVISI TRANSACTI ONAL BANKING SERVICES (TBS) | G15: TRF/PAY/TOP-UP ECHANNEL | 6010043330000011 | BNI DIRECT | BILL PAYMENT (PLN PREPAID ) NO :45031588457 | H15: Listrik / PLN | I15: D | J15: 1000000 | K15: 0 | L15: 6768201
A16: 12 | B16: Jan 2026 | C16: 14/01/2026 13.43.32 | D16: 14/01/2026 13.43.32 | E16: 967925 | F16: DIVISI TRANSACTI ONAL BANKING SERVICES (TBS) | G16: TRF/PAY/TOP-UP ECHANNEL | 6010043330000011 | BNI DIRECT | BIAYA ADMIN (PLN PREPAID ) NO :45031588457 8878 | H16: Listrik / PLN | I16: D | J16: 3500 | K16: 0 | L16: 6764701
... A133: 129 | B133: Jul 2026 | C133: 31/07/2026 08.00.00 | D133: 31/07/2026 08.00.00 | E133: 932640 | F133: INTERNAL BRANCH | G133: BIAYA ADM REK | H133: Biaya Admin / Bank | I133: D | J133: 25000 | K133: 0 | L133: 132824063
B134: TOTAL | J134: =SUM(J5:J133) -> 2238150351 | K134: =SUM(K5:K133) -> 2368658312 | L134: 132824063

Sheet Jan 2026
A1: REKAP TRANSAKSI REKENING KORAN BNI - PERIODE JAN 2026
A2: PT HIJAU SEJAHTERA BERSAMA | Periode: 01-Jan-26 - 31-Jan-26 | Source: 2026-01_RK_BNI.pdf
A4: SALDO AWAL | C4: TOTAL DEBET (KELUAR) | E4: TOTAL KREDIT (MASUK) | G4: SALDO AKHIR
A5: 2316102 | C5: =SUM(I8:I25) -> 27174981 | E5: =SUM(J8:J25) -> 28500010 | G5: 3641131
A7: No | B7: Posting Date | C7: Effective Date | D7: No. Jurnal | E7: Cabang / Branch | F7: Uraian / Deskripsi Transaksi | G7: Kategori | H7: DB/CR | I7: Debet / Keluar (Rp) | J7: Kredit / Masuk (Rp) | K7: Saldo Akhir (Rp)
A8: 1 | B8: 09/01/2026 11.26.40 | C8: 09/01/2026 11.26.40 | D8: 905653 | E8: INTERNET BANKING | F8: TRF/PAY/TOP-UP ECHANNEL | PEMINDAHAN DARI 1140010073537 | 0000000000000000 | WIJI INDRAYANI Lainnya | G8: Transfer / Pemindahan | H8: K | I8: 0 | J8: 5500000 | K8: 7816102
A9: 2 | B9: 09/01/2026 11.35.14 | C9: 09/01/2026 11.35.14 | D9: 211467 | E9: DIVISI TRANSACTI ONAL BANKING SERVICES (TBS) | F9: TRANSFER KE | BILL PAYMENT (MPN G2 IDR ) NO :041659442003798 | G9: Pajak (MPN G2) | H9: D | I9: 13240 | J9: 0 | K9: 7802862
A10: 3 | B10: 09/01/2026 11.35.14 | C10: 09/01/2026 11.35.14 | D10: 201348 | E10: DIVISI TRANSACTI ONAL BANKING SERVICES (TBS) | F10: TRANSFER KE | 8888890001020743 67DBD5B548FB84C4 | BILL PAYMENT (H2H BPJS KES) NO :67DBD5B548FB84C4 | G10: BPJS Kesehatan | H10: D | I10: 3804623 | J10: 0 | K10: 3998239
A11: 4 | B11: 09/01/2026 11.35.15 | C11: 09/01/2026 11.35.15 | D11: 212011 | E11: INTERNAL | F11: TRF/PAY/TOP-UP ECHANNEL | PEMINDAHAN KE 13001017205539 | 6010047890623568 | BNI DIRECT | G11: Transfer / Pemindahan | H11: D | I11: 540000 | J11: 0 | K11: 3458239
A12: 5 | B12: 09/01/2026 00.00.00 | C12: 09/01/2026 00.00.00 | D12: 212011 | E12: INTERNAL DIVISI | F12: BY TRX ATM PRIMA | G12: Biaya Admin / Bank | H12: D | I12: 6500 | J12: 0 | K12: 3451739
A13: 6 | B13: 09/01/2026 11.35.16 | C13: 09/01/2026 11.35.16 | D13: 201906 | E13: TRANSACTI ONAL BANKING SERVICES (TBS) | F13: TRANSFER KE | BILL PAYMENT (H2H BPJS TK ) NO :418307362000 | G13: BPJS Ketenagakerjaan | H13: D | I13: 1250475 | J13: 0 | K13: 2201264
A14: 7 | B14: 14/01/2026 10.18.57 | C14: 14/01/2026 10.18.57 | D14: 936510 | E14: INTERNET BANKING | F14: TRF/PAY/TOP-UP ECHANNEL | PEMINDAHAN DARI 1140016063946 | 0000000000000000 | HIJAU SEJAHTERA BERS BI FAST Transfer | G14: Transfer BI-FAST | H14: K | I14: 0 | J14: 23000000 | K14: 25201264
A15: 8 | B15: 14/01/2026 13.43.32 | C15: 14/01/2026 13.43.32 | D15: 342099 | E15: DIVISI TRANSACTI ONAL BANKING SERVICES (TBS) | F15: TRANSFER KE | BILL PAYMENT (MPN G2 IDR ) NO :030810890597019 | G15: Pajak (MPN G2) | H15: D | I15: 16429563 | J15: 0 | K15: 8771701
A16: 9 | B16: 14/01/2026 13.43.31 | C16: 14/01/2026 13.43.31 | D16: 968792 | E16: DIVISI TRANSACTI ONAL BANKING SERVICES (TBS) | F16: TRF/PAY/TOP-UP ECHANNEL | 6010043330000011 | BNI DIRECT | BILL PAYMENT (PLN PREPAID ) NO :45039450379 | G16: Listrik / PLN | H16: D | I16: 1000000 | J16: 0 | K16: 7771701
A17: 10 | B17: 14/01/2026 13.43.31 | C17: 14/01/2026 13.43.31 | D17: 968792 | E17: DIVISI TRANSACTI ONAL BANKING SERVICES (TBS) | F17: TRF/PAY/TOP-UP ECHANNEL | 6010043330000011 | BNI DIRECT | BIAYA ADMIN (PLN PREPAID ) NO :45039450379 4505 | G17: Listrik / PLN | H17: D | I17: 3500 | J17: 0 | K17: 7768201
A18: 11 | B18: 14/01/2026 13.43.32 | C18: 14/01/2026 13.43.32 | D18: 967925 | E18: DIVISI TRANSACTI ONAL BANKING SERVICES (TBS) | F18: TRF/PAY/TOP-UP ECHANNEL | 6010043330000011 | BNI DIRECT | BILL PAYMENT (PLN PREPAID ) NO :45031588457 | G18: Listrik / PLN | H18: D | I18: 1000000 | J18: 0 | K18: 6768201
A19: 12 | B19: 14/01/2026 13.43.32 | C19: 14/01/2026 13.43.32 | D19: 967925 | E19: DIVISI TRANSACTI ONAL BANKING SERVICES (TBS) | F19: TRF/PAY/TOP-UP ECHANNEL | 6010043330000011 | BNI DIRECT | BIAYA ADMIN (PLN PREPAID ) NO :45031588457 8878 | G19: Listrik / PLN | H19: D | I19: 3500 | J19: 0 | K19: 6764701
... A25: 18 | B25: 31/01/2026 08.00.00 | C25: 31/01/2026 08.00.00 | D25: 933309 | E25: INTERNAL BRANCH | F25: BIAYA ADM REK | G25: Biaya Admin / Bank | H25: D | I25: 25000 | J25: 0 | K25: 3641131
B26: TOTAL | I26: =SUM(I8:I25) -> 27174981 | J26: =SUM(J8:J25) -> 28500010 | K26: 3641131

Sheet Feb 2026
A1: REKAP TRANSAKSI REKENING KORAN BNI - PERIODE FEB 2026
A2: PT HIJAU SEJAHTERA BERSAMA | Periode: 01-Feb-26 - 28-Feb-26 | Source: 2026-02_RK_BNI.pdf
A4: SALDO AWAL | C4: TOTAL DEBET (KELUAR) | E4: TOTAL KREDIT (MASUK) | G4: SALDO AKHIR
A5: 3641131 | C5: =SUM(I8:I19) -> 34532589 | E5: =SUM(J8:J19) -> 32050296 | G5: 1158838
A7: No | B7: Posting Date | C7: Effective Date | D7: No. Jurnal | E7: Cabang / Branch | F7: Uraian / Deskripsi Transaksi | G7: Kategori | H7: DB/CR | I7: Debet / Keluar (Rp) | J7: Kredit / Masuk (Rp) | K7: Saldo Akhir (Rp)
A8: 1 | B8: 09/02/2026 17.40.46 | C8: 09/02/2026 17.40.46 | D8: 959786 | E8: INTERNAL | F8: TRF/PAY/TOP-UP ECHANNEL | PEMINDAHAN DARI 13001002256309 | 5221844701800446 | OM360002000088887176 | G8: Transfer / Pemindahan | H8: K | I8: 0 | J8: 23000000 | K8: 26641131
A9: 2 | B9: 10/02/2026 15.38.21 | C9: 10/02/2026 15.38.21 | D9: 046901 | E9: DIVISI TRANSACTI ONAL BANKING SERVICES (TBS) | F9: TRANSFER KE | BILL PAYMENT (MPN G2 IDR ) NO :041609162191703 | G9: Pajak (MPN G2) | H9: D | I9: 23466520 | J9: 0 | K9: 3174611
A10: 3 | B10: 10/02/2026 15.43.28 | C10: 10/02/2026 15.43.28 | D10: 971623 | E10: DIVISI TRANSACTI ONAL BANKING SERVICES (TBS) | F10: TRANSFER KE | PEMINDAHAN KE 845736142 Ibu WIJI INDRAYANI | transfer TRF TO:000000000845736142 | G10: Transfer / Pemindahan | H10: D | I10: 3000000 | J10: 0 | K10: 174611
A11: 4 | B11: 10/02/2026 16.34.28 | C11: 10/02/2026 16.34.28 | D11: 974164 | E11: INTERNAL | F11: TRF/PAY/TOP-UP ECHANNEL | PEMINDAHAN DARI 1177317888 | 0232051177317888 | S1ACIB9505 9895 | G11: Transfer / Pemindahan | H11: K | I11: 0 | J11: 5000000 | K11: 5174611
A12: 5 | B12: 10/02/2026 16.39.17 | C12: 10/02/2026 16.39.17 | D12: 962124 | E12: INTERNET BANKING | F12: TRF/PAY/TOP-UP ECHANNEL | PEMINDAHAN DARI 1140010073537 | 0000000000000000 | WIJI INDRAYANI Lainnya | G12: Transfer / Pemindahan | H12: K | I12: 0 | J12: 1000000 | K12: 6174611
A13: 6 | B13: 10/02/2026 16.41.06 | C13: 10/02/2026 16.41.06 | D13: 432085 | E13: DIVISI TRANSACTI ONAL BANKING SERVICES (TBS) | F13: TRANSFER KE | BILL PAYMENT (H2H BPJS TK ) NO :418307362000 | G13: BPJS Ketenagakerjaan | H13: D | I13: 1336446 | J13: 0 | K13: 4838165
A14: 7 | B14: 10/02/2026 16.41.07 | C14: 10/02/2026 16.41.07 | D14: 432698 | E14: DIVISI TRANSACTI ONAL BANKING SERVICES | F14: TRANSFER KE | 8888890001020743 691CEE36EE37A8D5 | BILL PAYMENT (H2H BPJS KES) NO :691CEE36EE37A8D5 | G14: BPJS Kesehatan | H14: D | I14: 3804623 | J14: 0 | K14: 1033542
A15: 8 | B15: 15/02/2026 10.52.42 | C15: 15/02/2026 10.52.42 | D15: 917095 | E15: (TBS) INTERNET BANKING | F15: TRF/PAY/TOP-UP ECHANNEL | PEMINDAHAN DARI 1140016063946 | | G15: Transfer / Pemindahan | H15: K | I15: 0 | J15: 3000000 | K15: 4033542
A16: 9 | B16: 15/02/2026 10.55.12 | C16: 15/02/2026 10.55.12 | D16: 507558 | E16: DIVISI TRANSACTI ONAL BANKING SERVICES (TBS) | F16: 0000000000000000 | HIJAU SEJAHTERA BERS BI FAST Transfer TRANSFER KE | BILL PAYMENT (MPN G2 IDR ) NO :041718249508555 | G16: Pajak (MPN G2) | H16: D | I16: 2900000 | J16: 0 | K16: 1133542
A17: 10 | B17: 25/02/2026 14.12.25 | C17: 25/02/2026 14.12.25 | D17: 991826 | E17: INTERNET BANKING | F17: TRF/PAY/TOP-UP ECHANNEL | PEMINDAHAN DARI 1177317888 | 0000000000000000 | HIJAU SEJAHTERA BERSAMA - | G17: Transfer / Pemindahan | H17: K | I17: 0 | J17: 50000 | K17: 1183542
A18: 11 | B18: 28/02/2026 00.09.41 | C18: 28/02/2026 00.09.41 | D18: 933160 | E18: INTERNAL BRANCH | F18: JASA GIRO/BUNGA | G18: Jasa Giro | H18: K | I18: 0 | J18: 296 | K18: 1183838
A19: 12 | B19: 28/02/2026 08.00.00 | C19: 28/02/2026 08.00.00 | D19: 933160 | E19: INTERNAL BRANCH | F19: BIAYA ADM REK | G19: Biaya Admin / Bank | H19: D | I19: 25000 | J19: 0 | K19: 1158838
B20: TOTAL | I20: =SUM(I8:I19) -> 34532589 | J20: =SUM(J8:J19) -> 32050296 | K20: 1158838

Sheet Mar 2026
A1: REKAP TRANSAKSI REKENING KORAN BNI - PERIODE MAR 2026
A2: PT HIJAU SEJAHTERA BERSAMA | Periode: 01-Mar-26 - 31-Mar-26 | Source: 2026-03_RK_BNI.pdf
A4: SALDO AWAL | C4: TOTAL DEBET (KELUAR) | E4: TOTAL KREDIT (MASUK) | G4: SALDO AKHIR
A5: 1158838 | C5: =SUM(I8:I16) -> 8115149 | E5: =SUM(J8:J16) -> 142069630 | G5: 135113319
A7: No | B7: Posting Date | C7: Effective Date | D7: No. Jurnal | E7: Cabang / Branch | F7: Uraian / Deskripsi Transaksi | G7: Kategori | H7: DB/CR | I7: Debet / Keluar (Rp) | J7: Kredit / Masuk (Rp) | K7: Saldo Akhir (Rp)
A8: 1 | B8: 11/03/2026 17.13.20 | C8: 11/03/2026 17.13.20 | D8: 933609 | E8: INTERNET BANKING | F8: TRF/PAY/TOP-UP ECHANNEL | PEMINDAHAN DARI 1140016063946 | 0000000000000000 | HIJAU SEJAHTERA BERS BI FAST Transfer | G8: Transfer BI-FAST | H8: K | I8: 0 | J8: 8100000 | K8: 9258838
A9: 2 | B9: 12/03/2026 10.03.26 | C9: 12/03/2026 10.03.26 | D9: 646956 | E9: DIVISI TRANSACTI ONAL BANKING SERVICES (TBS) | F9: TRANSFER KE | BILL PAYMENT (MPN G2 IDR ) NO :041888682441745 | G9: Pajak (MPN G2) | H9: D | I9: 2900000 | J9: 0 | K9: 6358838
A10: 3 | B10: 12/03/2026 11.51.31 | C10: 12/03/2026 11.51.31 | D10: 799108 | E10: DIVISI TRANSACTI ONAL BANKING SERVICES (TBS) | F10: TRANSFER KE | 8888890001020743 9E3BD4790FA1E6C9 | BILL PAYMENT (H2H BPJS KES) NO :9E3BD4790FA1E6C9 | G10: BPJS Kesehatan | H10: D | I10: 3804623 | J10: 0 | K10: 2554215
A11: 4 | B11: 12/03/2026 11.51.32 | C11: 12/03/2026 11.51.32 | D11: 799682 | E11: DIVISI TRANSACTI ONAL BANKING SERVICES (TBS) | F11: TRANSFER KE | BILL PAYMENT (H2H BPJS TK ) NO :418307362000 | G11: BPJS Ketenagakerjaan | H11: D | I11: 1381976 | J11: 0 | K11: 1172239
A12: 5 | B12: 26/03/2026 20.05.46 | C12: 26/03/2026 20.05.46 | D12: 988637 | E12: INTERNET BANKING | F12: TRF/PAY/TOP-UP ECHANNEL | PEMINDAHAN DARI 1140016063946 | 0000000000000000 | HIJAU SEJAHTERA BERS BI FAST Transfer | G12: Transfer BI-FAST | H12: K | I12: 0 | J12: 133726880 | K12: 134899119
A13: 6 | B13: 26/03/2026 20.10.57 | C13: 26/03/2026 20.10.57 | D13: 914835 | E13: INTERNET BANKING | F13: TRF/PAY/TOP-UP ECHANNEL | PEMINDAHAN DARI 1140016063946 | 0000000000000000 | HIJAU SEJAHTERA BERS BI FAST | G13: Transfer BI-FAST | H13: K | I13: 0 | J13: 225000 | K13: 135124119
A14: 7 | B14: 31/03/2026 00.59.25 | C14: 31/03/2026 00.59.25 | D14: 933015 | E14: INTERNAL BRANCH | F14: Transfer JASA GIRO/BUNGA | G14: Jasa Giro | H14: K | I14: 0 | J14: 17750 | K14: 135141869
A15: 8 | B15: 31/03/2026 00.59.25 | C15: 31/03/2026 00.59.25 | D15: 933015 | E15: INTERNAL BRANCH | F15: PPH | G15: Pajak PPh | H15: D | I15: 3550 | J15: 0 | K15: 135138319
A16: 9 | B16: 31/03/2026 08.00.00 | C16: 31/03/2026 08.00.00 | D16: 933015 | E16: INTERNAL BRANCH | F16: BIAYA ADM REK | G16: Biaya Admin / Bank | H16: D | I16: 25000 | J16: 0 | K16: 135113319
B17: TOTAL | I17: =SUM(I8:I16) -> 8115149 | J17: =SUM(J8:J16) -> 142069630 | K17: 135113319

Sheet Apr 2026
A1: REKAP TRANSAKSI REKENING KORAN BNI - PERIODE APR 2026
A2: PT HIJAU SEJAHTERA BERSAMA | Periode: 01-Apr-26 - 30-Apr-26 | Source: 2026-04_RK_BNI.pdf
A4: SALDO AWAL | C4: TOTAL DEBET (KELUAR) | E4: TOTAL KREDIT (MASUK) | G4: SALDO AKHIR
A5: 135113319 | C5: =SUM(I8:I30) -> 646720434 | E5: =SUM(J8:J30) -> 554778538 | G5: 43171423
A7: No | B7: Posting Date | C7: Effective Date | D7: No. Jurnal | E7: Cabang / Branch | F7: Uraian / Deskripsi Transaksi | G7: Kategori | H7: DB/CR | I7: Debet / Keluar (Rp) | J7: Kredit / Masuk (Rp) | K7: Saldo Akhir (Rp)
A8: 1 | B8: 06/04/2026 13.24.11 | C8: 06/04/2026 13.24.11 | D8: 952533 | E8: DIVISI TRANSACTI ONAL BANKING SERVICES (TBS) | F8: TRF/PAY/TOP-UP ECHANNEL | PEMINDAHAN KE 1140010073537 | 0000000000000000 | 1140010073537 | G8: Transfer / Pemindahan | H8: D | I8: 20000000 | J8: 0 | K8: 115113319
A9: 2 | B9: 06/04/2026 00.00.00 | C9: 06/04/2026 00.00.00 | D9: 952533 | E9: DIVISI TRANSACTI ONAL BANKING SERVICES (TBS) | F9: BY TRX BIFAST | G9: Transfer BI-FAST | H9: D | I9: 2500 | J9: 0 | K9: 115110819
A10: 3 | B10: 06/04/2026 14.35.48 | C10: 06/04/2026 14.35.48 | D10: 984793 | E10: INTERNAL | F10: TRF/PAY/TOP-UP ECHANNEL | PEMINDAHAN DARI 13001002256309 | 5221844701800446 | OM360002000088886405 | G10: Transfer / Pemindahan | H10: K | I10: 0 | J10: 20000000 | K10: 135110819
A11: 4 | B11: 08/04/2026 09.36.20 | C11: 08/04/2026 09.36.20 | D11: 967640 | E11: INTERNET BANKING | F11: TRF/PAY/TOP-UP ECHANNEL | PEMINDAHAN DARI 1140016063946 | 0000000000000000 | HIJAU SEJAHTERA BERS BI FAST Transfer | G11: Transfer BI-FAST | H11: K | I11: 0 | J11: 237047200 | K11: 372158019
A12: 5 | B12: 09/04/2026 14.38.30 | C12: 09/04/2026 14.38.30 | D12: 589484 | E12: DIVISI TRANSACTI ONAL BANKING SERVICES (TBS) | F12: TRANSFER KE | BILL PAYMENT (MPN G2 IDR ) NO :041953485875141 | G12: Pajak (MPN G2) | H12: D | I12: 2900000 | J12: 0 | K12: 369258019
A13: 6 | B13: 11/04/2026 17.12.06 | C13: 11/04/2026 17.12.06 | D13: 961968 | E13: DIVISI TRANSACTI ONAL BANKING SERVICES (TBS) | F13: TRF/PAY/TOP-UP ECHANNEL | PEMINDAHAN KE 1140006499076 | 0000000000000000 | 1140006499076 | G13: Transfer / Pemindahan | H13: D | I13: 132500000 | J13: 0 | K13: 236758019
A14: 7 | B14: 11/04/2026 00.00.00 | C14: 11/04/2026 00.00.00 | D14: 961968 | E14: DIVISI TRANSACTI ONAL BANKING SERVICES | F14: BY TRX BIFAST | G14: Transfer BI-FAST | H14: D | I14: 2500 | J14: 0 | K14: 236755519
A15: 8 | B15: 13/04/2026 10.26.51 | C15: 13/04/2026 10.26.51 | D15: 251926 | E15: (TBS) METRO | F15: SETOR TUNAI | HIJAU | G15: Setor Tunai | H15: K | I15: 0 | J15: 132500000 | K15: 369255519
A16: 9 | B16: 23/04/2026 13.17.56 | C16: 23/04/2026 13.17.56 | D16: 211085 | E16: DIVISI TRANSACTI ONAL BANKING SERVICES (TBS) | F16: SEJAHTERA BERSAMA TRANSFER KE | BILL PAYMENT (MPN G2 IDR ) NO :041913293939893 | G16: Pajak (MPN G2) | H16: D | I16: 7300 | J16: 0 | K16: 369248219
A17: 10 | B17: 23/04/2026 13.17.57 | C17: 23/04/2026 13.17.57 | D17: 203874 | E17: DIVISI TRANSACTI ONAL BANKING SERVICES (TBS) | F17: TRANSFER KE | BILL PAYMENT (MPN G2 IDR ) NO :041971665471622 | G17: Pajak (MPN G2) | H17: D | I17: 6160 | J17: 0 | K17: 369242059
A18: 11 | B18: 23/04/2026 13.17.59 | C18: 23/04/2026 13.17.59 | D18: 204399 | E18: DIVISI TRANSACTI ONAL BANKING SERVICES (TBS) | F18: TRANSFER KE | BILL PAYMENT (MPN G2 IDR ) NO :041901068275288 | G18: Pajak (MPN G2) | H18: D | I18: 8800 | J18: 0 | K18: 369233259
A19: 12 | B19: 23/04/2026 13.33.58 | C19: 23/04/2026 13.33.58 | D19: 988744 | E19: DIVISI TRANSACTI ONAL BANKING SERVICES (TBS) | F19: TRF/PAY/TOP-UP ECHANNEL | PEMINDAHAN KE 1140010073537 | 0000000000000000 | 1140010073537 TRANSFER DANA | G19: Transfer / Pemindahan | H19: D | I19: 5000000 | J19: 0 | K19: 364233259
... A30: 23 | B30: 30/04/2026 08.00.00 | C30: 30/04/2026 08.00.00 | D30: 932873 | E30: INTERNAL BRANCH | F30: BIAYA ADM REK | G30: Biaya Admin / Bank | H30: D | I30: 25000 | J30: 0 | K30: 43171423
B31: TOTAL | I31: =SUM(I8:I30) -> 646720434 | J31: =SUM(J8:J30) -> 554778538 | K31: 43171423

Sheet Mei 2026
A1: REKAP TRANSAKSI REKENING KORAN BNI - PERIODE MEI 2026
A2: PT HIJAU SEJAHTERA BERSAMA | Periode: 01-May-26 - 31-May-26 | Source: 2026-05_RK_BNI.pdf
A4: SALDO AWAL | C4: TOTAL DEBET (KELUAR) | E4: TOTAL KREDIT (MASUK) | G4: SALDO AKHIR
A5: 43171423 | C5: =SUM(I8:I29) -> 551530582 | E5: =SUM(J8:J29) -> 514791752 | G5: 6432593
A7: No | B7: Posting Date | C7: Effective Date | D7: No. Jurnal | E7: Cabang / Branch | F7: Uraian / Deskripsi Transaksi | G7: Kategori | H7: DB/CR | I7: Debet / Keluar (Rp) | J7: Kredit / Masuk (Rp) | K7: Saldo Akhir (Rp)
A8: 1 | B8: 08/05/2026 10.57.15 | C8: 08/05/2026 10.57.15 | D8: 927652 | E8: INTERNET BANKING | F8: TRF/PAY/TOP-UP ECHANNEL | PEMINDAHAN DARI 1140016063946 | 0000000000000000 | HIJAU SEJAHTERA BERS BI FAST Transfer | G8: Transfer BI-FAST | H8: K | I8: 0 | J8: 233988000 | K8: 277159423
A9: 2 | B9: 08/05/2026 11.19.51 | C9: 08/05/2026 11.19.51 | D9: 945955 | E9: INTERNET BANKING | F9: TRF/PAY/TOP-UP ECHANNEL | PEMINDAHAN DARI 1140016063946 | 0000000000000000 | HIJAU SEJAHTERA BERS BI FAST Transfer | G9: Transfer BI-FAST | H9: K | I9: 0 | J9: 13350000 | K9: 290509423
A10: 3 | B10: 08/05/2026 13.46.03 | C10: 08/05/2026 13.46.03 | D10: 022147 | E10: DIVISI TRANSACTI ONAL BANKING SERVICES (TBS) | F10: TRANSFER KE | BILL PAYMENT (MPN G2 IDR ) NO :042068859784941 | G10: Pajak (MPN G2) | H10: D | I10: 4700000 | J10: 0 | K10: 285809423
A11: 4 | B11: 08/05/2026 13.46.04 | C11: 08/05/2026 13.46.04 | D11: 022383 | E11: DIVISI TRANSACTI ONAL BANKING SERVICES (TBS) | F11: TRANSFER KE | 8888890001020743 5C5A29D6A88DB869 | BILL PAYMENT (H2H BPJS KES) NO :5C5A29D6A88DB869 | G11: BPJS Kesehatan | H11: D | I11: 7213041 | J11: 0 | K11: 278596382
A12: 5 | B12: 09/05/2026 10.28.25 | C12: 09/05/2026 10.28.25 | D12: 556703 | E12: DIVISI TRANSACTI ONAL BANKING SERVICES (TBS) | F12: TRANSFER KE | BILL PAYMENT (MPN G2 IDR ) NO :042025827670792 | G12: Pajak (MPN G2) | H12: D | I12: 14701125 | J12: 0 | K12: 263895257
A13: 6 | B13: 09/05/2026 10.28.25 | C13: 09/05/2026 10.28.25 | D13: 569504 | E13: DIVISI TRANSACTI ONAL BANKING SERVICES (TBS) | F13: TRANSFER KE | BILL PAYMENT (H2H BPJS TK ) NO :260500321658 | G13: BPJS Ketenagakerjaan | H13: D | I13: 1381976 | J13: 0 | K13: 262513281
A14: 7 | B14: 09/05/2026 10.28.26 | C14: 09/05/2026 10.28.26 | D14: 569738 | E14: DIVISI TRANSACTI ONAL BANKING SERVICES (TBS) | F14: TRANSFER KE | BILL PAYMENT (MPN G2 IDR ) NO :042093552095593 | G14: Pajak (MPN G2) | H14: D | I14: 4760 | J14: 0 | K14: 262508521
A15: 8 | B15: 18/05/2026 15.24.40 | C15: 18/05/2026 15.24.40 | D15: 606950 | E15: DIVISI OPERASIO NAL DIVISI | F15: KREDIT LAIN-LAIN | 013 PT AKR CORPORIN INV 050-054 OAT | G15: Lainnya | H15: K | I15: 0 | J15: 38653300 | K15: 301161821
A16: 9 | B16: 19/05/2026 14.12.20 | C16: 19/05/2026 14.12.20 | D16: 991389 | E16: TRANSACTI ONAL BANKING SERVICES (TBS) | F16: TRF/PAY/TOP-UP ECHANNEL | PEMINDAHAN KE 1140010073537 | 0000000000000000 | 1140010073537 | G16: Transfer / Pemindahan | H16: D | I16: 38000000 | J16: 0 | K16: 263161821
A17: 10 | B17: 19/05/2026 00.00.00 | C17: 19/05/2026 00.00.00 | D17: 991389 | E17: DIVISI TRANSACTI ONAL BANKING SERVICES (TBS) | F17: BY TRX BIFAST | G17: Transfer BI-FAST | H17: D | I17: 2500 | J17: 0 | K17: 263159321
A18: 11 | B18: 21/05/2026 10.23.48 | C18: 21/05/2026 10.23.48 | D18: 627559 | E18: DIVISI TRANSACTI ONAL BANKING SERVICES (TBS) | F18: TRANSFER KE | BILL PAYMENT (MPN G2 IDR ) NO :042015443408172 | G18: Pajak (MPN G2) | H18: D | I18: 7656472 | J18: 0 | K18: 255502849
A19: 12 | B19: 21/05/2026 10.23.49 | C19: 21/05/2026 10.23.49 | D19: 627862 | E19: DIVISI TRANSACTI ONAL BANKING SERVICES (TBS) | F19: TRANSFER KE | BILL PAYMENT (MPN G2 IDR ) NO :042016540838246 | G19: Pajak (MPN G2) | H19: D | I19: 80000 | J19: 0 | K19: 255422849
... A29: 22 | B29: 31/05/2026 08.00.00 | C29: 31/05/2026 08.00.00 | D29: 932713 | E29: INTERNAL BRANCH | F29: BIAYA ADM REK | G29: Biaya Admin / Bank | H29: D | I29: 25000 | J29: 0 | K29: 6432593
B30: TOTAL | I30: =SUM(I8:I29) -> 551530582 | J30: =SUM(J8:J29) -> 514791752 | K30: 6432593

Sheet Jun 2026
A1: REKAP TRANSAKSI REKENING KORAN BNI - PERIODE JUN 2026
A2: PT HIJAU SEJAHTERA BERSAMA | Periode: 01-Jun-26 - 30-Jun-26 | Source: 2026-06_RK_BNI.pdf
A4: SALDO AWAL | C4: TOTAL DEBET (KELUAR) | E4: TOTAL KREDIT (MASUK) | G4: SALDO AKHIR
A5: 6432593 | C5: =SUM(I8:I39) -> 685260678 | E5: =SUM(J8:J39) -> 803248487 | G5: 124420402
A7: No | B7: Posting Date | C7: Effective Date | D7: No. Jurnal | E7: Cabang / Branch | F7: Uraian / Deskripsi Transaksi | G7: Kategori | H7: DB/CR | I7: Debet / Keluar (Rp) | J7: Kredit / Masuk (Rp) | K7: Saldo Akhir (Rp)
A8: 1 | B8: 03/06/2026 18.45.36 | C8: 03/06/2026 18.45.36 | D8: 917113 | E8: INTERNET BANKING | F8: TRANSFER DARI | PEMINDAHAN DARI 845736142 Ibu WIJI INDRAYANI | G8: Transfer / Pemindahan | H8: K | I8: 0 | J8: 100000000 | K8: 106432593
A9: 2 | B9: 03/06/2026 18.47.12 | C9: 03/06/2026 18.47.12 | D9: 927769 | E9: INTERNET BANKING DIVISI | F9: TRANSFER DARI | PEMINDAHAN DARI 845736142 Ibu WIJI INDRAYANI | G9: Transfer / Pemindahan | H9: K | I9: 0 | J9: 100000000 | K9: 206432593
A10: 3 | B10: 03/06/2026 19.02.42 | C10: 03/06/2026 19.02.42 | D10: 932606 | E10: TRANSACTI ONAL BANKING SERVICES (TBS) | F10: TRF/PAY/TOP-UP ECHANNEL | PEMINDAHAN KE 1140006499076 | 0000000000000000 | 1140006499076 | G10: Transfer / Pemindahan | H10: D | I10: 100000000 | J10: 0 | K10: 106432593
A11: 4 | B11: 03/06/2026 00.00.00 | C11: 03/06/2026 00.00.00 | D11: 932606 | E11: DIVISI TRANSACTI ONAL BANKING SERVICES (TBS) | F11: BY TRX BIFAST | G11: Transfer BI-FAST | H11: D | I11: 2500 | J11: 0 | K11: 106430093
A12: 5 | B12: 03/06/2026 19.02.44 | C12: 03/06/2026 19.02.44 | D12: 932814 | E12: DIVISI TRANSACTI ONAL BANKING SERVICES (TBS) | F12: TRF/PAY/TOP-UP ECHANNEL | PEMINDAHAN KE 1170419282 | 0000000000000000 | 1170419282 | G12: Transfer / Pemindahan | H12: D | I12: 100000000 | J12: 0 | K12: 6430093
A13: 6 | B13: 03/06/2026 00.00.00 | C13: 03/06/2026 00.00.00 | D13: 932814 | E13: DIVISI TRANSACTI ONAL BANKING SERVICES (TBS) | F13: BY TRX BIFAST | G13: Transfer BI-FAST | H13: D | I13: 2500 | J13: 0 | K13: 6427593
A14: 7 | B14: 10/06/2026 14.50.05 | C14: 10/06/2026 14.50.05 | D14: 908771 | E14: INTERNET BANKING | F14: TRF/PAY/TOP-UP ECHANNEL | PEMINDAHAN DARI 1140010073537 | 0000000000000000 | WIJI INDRAYANI Lainnya | G14: Transfer / Pemindahan | H14: K | I14: 0 | J14: 19500000 | K14: 25927593
A15: 8 | B15: 10/06/2026 15.17.38 | C15: 10/06/2026 15.17.38 | D15: 462780 | E15: DIVISI TRANSACTI ONAL BANKING SERVICES | F15: TRANSFER KE | BILL PAYMENT (MPN G2 IDR ) NO :042176536412586 | G15: Pajak (MPN G2) | H15: D | I15: 4700000 | J15: 0 | K15: 21227593
A16: 9 | B16: 10/06/2026 15.17.39 | C16: 10/06/2026 15.17.39 | D16: 471132 | E16: (TBS) DIVISI | F16: TRANSFER KE | BILL PAYMENT | G16: Transfer / Pemindahan | H16: D | I16: 14701125 | J16: 0 | K16: 6526468
A17: 10 | B17: 15/06/2026 11.45.48 | C17: 15/06/2026 11.45.48 | D17: 139598 | E17: TRANSACTI ONAL BANKING SERVICES (TBS) DIVISI TRANSACTI ONAL BANKING SERVICES (TBS) | F17: (MPN G2 IDR ) NO :042189224513474 TRANSFER KE | 8888890001020743 3387CB69BE464EC3 | BILL PAYMENT (H2H BPJS KES) NO :3387CB69BE464EC3 | G17: Pajak (MPN G2) | H17: D | I17: 3408418 | J17: 0 | K17: 3118050
A18: 11 | B18: 15/06/2026 12.18.03 | C18: 15/06/2026 12.18.03 | D18: 920814 | E18: INTERNET BANKING | F18: TRF/PAY/TOP-UP ECHANNEL | PEMINDAHAN DARI 1140010073537 | 0000000000000000 | WIJI INDRAYANI Lainnya | G18: Transfer / Pemindahan | H18: K | I18: 0 | J18: 10000000 | K18: 13118050
A19: 12 | B19: 15/06/2026 14.02.13 | C19: 15/06/2026 14.02.13 | D19: 680179 | E19: DIVISI TRANSACTI ONAL BANKING SERVICES (TBS) | F19: TRANSFER KE | BILL PAYMENT (H2H BPJS TK ) NO :260600457796 | G19: BPJS Ketenagakerjaan | H19: D | I19: 2763952 | J19: 0 | K19: 10354098
... A39: 32 | B39: 30/06/2026 08.00.00 | C39: 30/06/2026 08.00.00 | D39: 932653 | E39: BRANCH INTERNAL BRANCH | F39: BIAYA ADM REK | G39: Biaya Admin / Bank | H39: D | I39: 25000 | J39: 0 | K39: 124420402
B40: TOTAL | I40: =SUM(I8:I39) -> 685260678 | J40: =SUM(J8:J39) -> 803248487 | K40: 124420402

Sheet Jul 2026
A1: REKAP TRANSAKSI REKENING KORAN BNI - PERIODE JUL 2026
A2: PT HIJAU SEJAHTERA BERSAMA | Periode: 01-Jul-26 - 31-Jul-26 | Source: 2026-07_RK_BNI.pdf
A4: SALDO AWAL | C4: TOTAL DEBET (KELUAR) | E4: TOTAL KREDIT (MASUK) | G4: SALDO AKHIR
A5: 124420402 | C5: =SUM(I8:I20) -> 284815938 | E5: =SUM(J8:J20) -> 293219599 | G5: 132824063
A7: No | B7: Posting Date | C7: Effective Date | D7: No. Jurnal | E7: Cabang / Branch | F7: Uraian / Deskripsi Transaksi | G7: Kategori | H7: DB/CR | I7: Debet / Keluar (Rp) | J7: Kredit / Masuk (Rp) | K7: Saldo Akhir (Rp)
A8: 1 | B8: 09/07/2026 16.06.35 | C8: 09/07/2026 16.06.35 | D8: 956955 | E8: INTERNAL | F8: TRF/PAY/TOP-UP ECHANNEL | PEMINDAHAN DARI 13001002256309 | 5221844701800446 | OM360002000088885856 | G8: Transfer / Pemindahan | H8: K | I8: 0 | J8: 100000 | K8: 124520402
A9: 2 | B9: 09/07/2026 16.17.29 | C9: 09/07/2026 16.17.29 | D9: 905664 | E9: INTERNET BANKING | F9: TRF/PAY/TOP-UP ECHANNEL | PEMINDAHAN DARI 1140016063946 | 0000000000000000 | HIJAU SEJAHTERA BERS BI FAST Transfer | G9: Transfer BI-FAST | H9: K | I9: 0 | J9: 147000000 | K9: 271520402
A10: 3 | B10: 13/07/2026 11.21.01 | C10: 13/07/2026 11.21.01 | D10: 755169 | E10: DIVISI TRANSACTI ONAL BANKING SERVICES (TBS) | F10: TRANSFER KE | BILL PAYMENT (MPN G2 IDR ) NO :042258879585184 | G10: Pajak (MPN G2) | H10: D | I10: 263945286 | J10: 0 | K10: 7575116
A11: 4 | B11: 13/07/2026 11.29.12 | C11: 13/07/2026 11.29.12 | D11: 296330 | E11: DIVISI TRANSACTI ONAL BANKING SERVICES (TBS) | F11: TRANSFER KE | BILL PAYMENT (MPN G2 IDR ) NO :042261619122698 | G11: Pajak (MPN G2) | H11: D | I11: 38600 | J11: 0 | K11: 7536516
A12: 5 | B12: 13/07/2026 11.37.26 | C12: 13/07/2026 11.37.26 | D12: 660332 | E12: DIVISI TRANSACTI ONAL BANKING SERVICES (TBS) | F12: TRANSFER KE | BILL PAYMENT (MPN G2 IDR ) NO :042225144614925 | G12: Pajak (MPN G2) | H12: D | I12: 4700000 | J12: 0 | K12: 2836516
A13: 6 | B13: 13/07/2026 11.51.01 | C13: 13/07/2026 11.51.01 | D13: 428587 | E13: DIVISI TRANSACTI ONAL BANKING SERVICES (TBS) | F13: TRANSFER KE | BILL PAYMENT (H2H BPJS TK ) NO :726073208233 | G13: BPJS Ketenagakerjaan | H13: D | I13: 1381976 | J13: 0 | K13: 1454540
A14: 7 | B14: 14/07/2026 08.59.17 | C14: 14/07/2026 08.59.17 | D14: 928682 | E14: INTERNET BANKING | F14: TRF/PAY/TOP-UP ECHANNEL | PEMINDAHAN DARI 1140016063946 | 0000000000000000 | HIJAU SEJAHTERA BERS BI FAST | G14: Transfer BI-FAST | H14: K | I14: 0 | J14: 14800000 | K14: 16254540
A15: 8 | B15: 14/07/2026 09.03.03 | C15: 14/07/2026 09.03.03 | D15: 319627 | E15: DIVISI | F15: Transfer TRANSFER KE | BILL PAYMENT | G15: Transfer / Pemindahan | H15: D | I15: 14701125 | J15: 0 | K15: 1553415
A16: 9 | B16: 15/07/2026 16.21.46 | C16: 15/07/2026 16.21.46 | D16: 570991 | E16: TRANSACTI ONAL BANKING SERVICES (TBS) DIVISI TRANSACTI ONAL BANKING SERVICES | F16: (MPN G2 IDR ) NO :042290219039655 TRANSFER KE | BILL PAYMENT (MPN G2 IDR ) NO :042262385688706 | G16: Pajak (MPN G2) | H16: D | I16: 13200 | J16: 0 | K16: 1540215
A17: 10 | B17: 30/07/2026 16.21.02 | C17: 30/07/2026 16.21.02 | D17: 020240 | E17: (TBS) DIVISI OPERASIO NAL | F17: KREDIT LAIN-LAIN | 002 TIGA OREGON PUT PEMB SOLAR PO 07/00006 | G17: Lainnya | H17: K | I17: 0 | J17: 131265844 | K17: 132806059
A18: 11 | B18: 31/07/2026 08.00.00 | C18: 31/07/2026 08.00.00 | D18: 932640 | E18: INTERNAL BRANCH | F18: JASA GIRO/BUNGA | G18: Jasa Giro | H18: K | I18: 0 | J18: 53755 | K18: 132859814
A19: 12 | B19: 31/07/2026 01.06.57 | C19: 31/07/2026 01.06.57 | D19: 932640 | E19: INTERNAL BRANCH | F19: PPH | G19: Pajak PPh | H19: D | I19: 10751 | J19: 0 | K19: 132849063
A20: 13 | B20: 31/07/2026 08.00.00 | C20: 31/07/2026 08.00.00 | D20: 932640 | E20: INTERNAL BRANCH | F20: BIAYA ADM REK | G20: Biaya Admin / Bank | H20: D | I20: 25000 | J20: 0 | K20: 132824063
B21: TOTAL | I21: =SUM(I8:I20) -> 284815938 | J21: =SUM(J8:J20) -> 293219599 | K21: 132824063
