Workbook

Sheet Ringkasan Eksekutif
A1: REKAPITULASI REKENING KORAN BANK BRI
A2: No. Rekening: 13001002256309 | Periode: Januari - Juli 2026 | Mata Uang: IDR
A4: SALDO AWAL (05/01/2026) | C4: TOTAL UANG MASUK (KREDIT) | E4: TOTAL UANG KELUAR (DEBET) | G4: NET CASH FLOW | I4: SALDO AKHIR (30/07/2026)
A5: 1372774.5 | C5: 4680849241 | E5: 4.5272452e+09 | G5: =C5-E5 -> 1.5360404e+08 | I5: 154976813
A7: 1. RINGKASAN ARUS KAS BULANAN (JANUARI - JULI 2026)
A8: Periode Bulan | B8: Saldo Awal (Rp) | C8: Total Masuk / Kredit (Rp) | D8: Total Keluar / Debet (Rp) | E8: Net Cash Flow (Rp) | F8: Saldo Akhir (Rp) | G8: Jumlah Transaksi
A9: Januari 2026 | B9: 1372774.5 | C9: =SUMIFS('Detail Transaksi'!I:I, 'Detail Transaksi'!B:B, "2026-01") -> 473115365 | D9: =SUMIFS('Detail Transaksi'!H:H, 'Detail Transaksi'!B:B, "2026-01") -> 473341439 | E9: =C9-D9 -> -226074 | F9: 1146700.5 | G9: =COUNTIFS('Detail Transaksi'!B:B, "2026-01") -> 34
A10: Februari 2026 | B10: 1146700.5 | C10: =SUMIFS('Detail Transaksi'!I:I, 'Detail Transaksi'!B:B, "2026-02") -> 536517008 | D10: =SUMIFS('Detail Transaksi'!H:H, 'Detail Transaksi'!B:B, "2026-02") -> 536466203 | E10: =C10-D10 -> 50805 | F10: 1197505.5 | G10: =COUNTIFS('Detail Transaksi'!B:B, "2026-02") -> 30
A11: Maret 2026 | B11: 1197505.5 | C11: =SUMIFS('Detail Transaksi'!I:I, 'Detail Transaksi'!B:B, "2026-03") -> 571817393 | D11: =SUMIFS('Detail Transaksi'!H:H, 'Detail Transaksi'!B:B, "2026-03") -> 572656281 | E11: =C11-D11 -> -838888 | F11: 358617.47 | G11: =COUNTIFS('Detail Transaksi'!B:B, "2026-03") -> 35
A12: April 2026 | B12: 358617.47 | C12: =SUMIFS('Detail Transaksi'!I:I, 'Detail Transaksi'!B:B, "2026-04") -> 1976867276 | D12: =SUMIFS('Detail Transaksi'!H:H, 'Detail Transaksi'!B:B, "2026-04") -> 1.9670064e+09 | E12: =C12-D12 -> 9860865.5 | F12: 10219483 | G12: =COUNTIFS('Detail Transaksi'!B:B, "2026-04") -> 35
A13: Mei 2026 | B13: 10219483 | C13: =SUMIFS('Detail Transaksi'!I:I, 'Detail Transaksi'!B:B, "2026-05") -> 157546791 | D13: =SUMIFS('Detail Transaksi'!H:H, 'Detail Transaksi'!B:B, "2026-05") -> 76518480 | E13: =C13-D13 -> 81028311 | F13: 91247794 | G13: =COUNTIFS('Detail Transaksi'!B:B, "2026-05") -> 18
A14: Juni 2026 | B14: 91247794 | C14: =SUMIFS('Detail Transaksi'!I:I, 'Detail Transaksi'!B:B, "2026-06") -> 475643583 | D14: =SUMIFS('Detail Transaksi'!H:H, 'Detail Transaksi'!B:B, "2026-06") -> 419689165 | E14: =C14-D14 -> 55954418 | F14: 147202212 | G14: =COUNTIFS('Detail Transaksi'!B:B, "2026-06") -> 29
A15: Juli 2026 | B15: 147202212 | C15: =SUMIFS('Detail Transaksi'!I:I, 'Detail Transaksi'!B:B, "2026-07") -> 489341825 | D15: =SUMIFS('Detail Transaksi'!H:H, 'Detail Transaksi'!B:B, "2026-07") -> 481567224 | E15: =C15-D15 -> 7774601 | F15: 154976813 | G15: =COUNTIFS('Detail Transaksi'!B:B, "2026-07") -> 30
A16: TOTAL / SALDO AKHIR | B16: 1372774.5 | C16: =SUM(C9:C15) -> 4680849241 | D16: =SUM(D9:D15) -> 4.5272452e+09 | E16: =C16-D16 -> 1.5360404e+08 | F16: 154976813 | G16: =SUM(G9:G15) -> 211
A18: 2. REKAPITULASI KATEGORI TRANSAKSI
A19: No | B19: Kategori Transaksi | C19: Jenis Arus Kas | D19: Total Debet (Pengeluaran) | E19: Total Kredit (Penerimaan) | F19: Net Cash Impact | G19: Jumlah Transaksi | H19: % Dari Total Arus
A20: 1 | B20: Penerimaan Penjualan (AKR Corporindo) | C20: Uang Masuk | D20: =SUMIFS('Detail Transaksi'!H:H, 'Detail Transaksi'!E:E, B20) -> 0 | E20: =SUMIFS('Detail Transaksi'!I:I, 'Detail Transaksi'!E:E, B20) -> 2487698344 | F20: =E20-D20 -> 2487698344 | G20: =COUNTIFS('Detail Transaksi'!E:E, B20) -> 32 | H20: =(D20+E20)/('Ringkasan Eksekutif'!C5+'Ringkasan Eksekutif'!E5) -> 0.2701643
A21: 2 | B21: Pencairan Kredit & Pemindahbukuan Internal | C21: Uang Masuk | D21: =SUMIFS('Detail Transaksi'!H:H, 'Detail Transaksi'!E:E, B21) -> 0 | E21: =SUMIFS('Detail Transaksi'!I:I, 'Detail Transaksi'!E:E, B21) -> 1640000000 | F21: =E21-D21 -> 1640000000 | G21: =COUNTIFS('Detail Transaksi'!E:E, B21) -> 2 | H21: =(D21+E21)/('Ringkasan Eksekutif'!C5+'Ringkasan Eksekutif'!E5) -> 0.17810417
A22: 3 | B22: Transfer Masuk BI-Fast / Pihak Ketiga | C22: Uang Masuk | D22: =SUMIFS('Detail Transaksi'!H:H, 'Detail Transaksi'!E:E, B22) -> 0 | E22: =SUMIFS('Detail Transaksi'!I:I, 'Detail Transaksi'!E:E, B22) -> 458000000 | F22: =E22-D22 -> 458000000 | G22: =COUNTIFS('Detail Transaksi'!E:E, B22) -> 12 | H22: =(D22+E22)/('Ringkasan Eksekutif'!C5+'Ringkasan Eksekutif'!E5) -> 0.049738847
A23: 4 | B23: Setoran Tunai | C23: Uang Masuk | D23: =SUMIFS('Detail Transaksi'!H:H, 'Detail Transaksi'!E:E, B23) -> 0 | E23: =SUMIFS('Detail Transaksi'!I:I, 'Detail Transaksi'!E:E, B23) -> 95000000 | F23: =E23-D23 -> 95000000 | G23: =COUNTIFS('Detail Transaksi'!E:E, B23) -> 2 | H23: =(D23+E23)/('Ringkasan Eksekutif'!C5+'Ringkasan Eksekutif'!E5) -> 0.01031701
A24: 5 | B24: Pendapatan Bunga Bank | C24: Uang Masuk | D24: =SUMIFS('Detail Transaksi'!H:H, 'Detail Transaksi'!E:E, B24) -> 0 | E24: =SUMIFS('Detail Transaksi'!I:I, 'Detail Transaksi'!E:E, B24) -> 150897 | F24: =E24-D24 -> 150897 | G24: =COUNTIFS('Detail Transaksi'!E:E, B24) -> 7 | H24: =(D24+E24)/('Ringkasan Eksekutif'!C5+'Ringkasan Eksekutif'!E5) -> 1.638743e-05
A25: 6 | B25: Transfer Keluar BI-Fast / Bank Transfer | C25: Uang Keluar | D25: =SUMIFS('Detail Transaksi'!H:H, 'Detail Transaksi'!E:E, B25) -> 2335445000 | E25: =SUMIFS('Detail Transaksi'!I:I, 'Detail Transaksi'!E:E, B25) -> 0 | F25: =E25-D25 -> -2335445000 | G25: =COUNTIFS('Detail Transaksi'!E:E, B25) -> 51 | H25: =(D25+E25)/('Ringkasan Eksekutif'!C5+'Ringkasan Eksekutif'!E5) -> 0.25362957
A26: 7 | B26: Pembayaran Angsuran, Pinjaman & Deplesi | C26: Uang Keluar | D26: =SUMIFS('Detail Transaksi'!H:H, 'Detail Transaksi'!E:E, B26) -> 1.7161633e+09 | E26: =SUMIFS('Detail Transaksi'!I:I, 'Detail Transaksi'!E:E, B26) -> 0 | F26: =E26-D26 -> -1.7161633e+09 | G26: =COUNTIFS('Detail Transaksi'!E:E, B26) -> 11 | H26: =(D26+E26)/('Ringkasan Eksekutif'!C5+'Ringkasan Eksekutif'!E5) -> 0.18637551
A27: 8 | B27: Transfer Antar Rekening (Overbooking) | C27: Uang Keluar | D27: =SUMIFS('Detail Transaksi'!H:H, 'Detail Transaksi'!E:E, B27) -> 4.1532844e+08 | E27: =SUMIFS('Detail Transaksi'!I:I, 'Detail Transaksi'!E:E, B27) -> 0 | F27: =E27-D27 -> -4.1532844e+08 | G27: =COUNTIFS('Detail Transaksi'!E:E, B27) -> 12 | H27: =(D27+E27)/('Ringkasan Eksekutif'!C5+'Ringkasan Eksekutif'!E5) -> 0.045104712
A28: 9 | B28: Biaya Provisi, Notaris & Asuransi Kredit | C28: Uang Keluar | D28: =SUMIFS('Detail Transaksi'!H:H, 'Detail Transaksi'!E:E, B28) -> 50550000 | E28: =SUMIFS('Detail Transaksi'!I:I, 'Detail Transaksi'!E:E, B28) -> 0 | F28: =E28-D28 -> -50550000 | G28: =COUNTIFS('Detail Transaksi'!E:E, B28) -> 6 | H28: =(D28+E28)/('Ringkasan Eksekutif'!C5+'Ringkasan Eksekutif'!E5) -> 0.0054897352
A29: 10 | B29: Pembayaran Tagihan Listrik & Pulsa | C29: Uang Keluar | D29: =SUMIFS('Detail Transaksi'!H:H, 'Detail Transaksi'!E:E, B29) -> 5400000 | E29: =SUMIFS('Detail Transaksi'!I:I, 'Detail Transaksi'!E:E, B29) -> 0 | F29: =E29-D29 -> -5400000 | G29: =COUNTIFS('Detail Transaksi'!E:E, B29) -> 12 | H29: =(D29+E29)/('Ringkasan Eksekutif'!C5+'Ringkasan Eksekutif'!E5) -> 0.00058644055
A30: 11 | B30: Pembayaran BPJS | C30: Uang Keluar | D30: =SUMIFS('Detail Transaksi'!H:H, 'Detail Transaksi'!E:E, B30) -> 3408418 | E30: =SUMIFS('Detail Transaksi'!I:I, 'Detail Transaksi'!E:E, B30) -> 0 | F30: =E30-D30 -> -3408418 | G30: =COUNTIFS('Detail Transaksi'!E:E, B30) -> 1 | H30: =(D30+E30)/('Ringkasan Eksekutif'!C5+'Ringkasan Eksekutif'!E5) -> 0.00037015454
A31: 12 | B31: Pembayaran e-Wallet (BRIVA/DANA) | C31: Uang Keluar | D31: =SUMIFS('Detail Transaksi'!H:H, 'Detail Transaksi'!E:E, B31) -> 550000 | E31: =SUMIFS('Detail Transaksi'!I:I, 'Detail Transaksi'!E:E, B31) -> 0 | F31: =E31-D31 -> -550000 | G31: =COUNTIFS('Detail Transaksi'!E:E, B31) -> 1 | H31: =(D31+E31)/('Ringkasan Eksekutif'!C5+'Ringkasan Eksekutif'!E5) -> 5.9730056e-05
A32: 13 | B32: Biaya Admin Bank & Transfer | C32: Uang Keluar | D32: =SUMIFS('Detail Transaksi'!H:H, 'Detail Transaksi'!E:E, B32) -> 370000 | E32: =SUMIFS('Detail Transaksi'!I:I, 'Detail Transaksi'!E:E, B32) -> 0 | F32: =E32-D32 -> -370000 | G32: =COUNTIFS('Detail Transaksi'!E:E, B32) -> 56 | H32: =(D32+E32)/('Ringkasan Eksekutif'!C5+'Ringkasan Eksekutif'!E5) -> 4.0182038e-05
A33: 14 | B33: Pajak Bunga Tabungan | C33: Uang Keluar | D33: =SUMIFS('Detail Transaksi'!H:H, 'Detail Transaksi'!E:E, B33) -> 30072 | E33: =SUMIFS('Detail Transaksi'!I:I, 'Detail Transaksi'!E:E, B33) -> 0 | F33: =E33-D33 -> -30072 | G33: =COUNTIFS('Detail Transaksi'!E:E, B33) -> 6 | H33: =(D33+E33)/('Ringkasan Eksekutif'!C5+'Ringkasan Eksekutif'!E5) -> 3.2658223e-06
B34: TOTAL KATEGORI | C34: - | D34: =SUM(D20:D33) -> 4.5272452e+09 | E34: =SUM(E20:E33) -> 4680849241 | F34: =E34-D34 -> 1.5360404e+08 | G34: =SUM(G20:G33) -> 211 | H34: =SUM(H20:H33) -> 1

Sheet Detail Transaksi
A1: DETAIL MUTASI TRANSAKSI REKENING KORAN BRI
A2: No. Rekening: 13001002256309 | Total Transaksi: 211 Items
A4: No | B4: Periode | C4: Tanggal & Waktu | D4: No. Rekening | E4: Kategori | F4: Keterangan / Remark | G4: Jenis (GL) | H4: Mutasi Debet (Rp) | I4: Mutasi Kredit (Rp) | J4: Saldo Akhir (Rp) | K4: User ID | L4: Kode Tran
A5: 1 | B5: 2026-01 | C5: 2026-01-05 13:54:10 | D5: 13001002256309 | E5: Penerimaan Penjualan (AKR Corporindo) | F5: PT AKR CORPORINDO-BANK PERMATA-INV 464,4 | G5: Kredit | H5: 0 | I5: 97242247 | J5: 98615021 | K5: BRI0372 | L5: 563
A6: 2 | B6: 2026-01 | C6: 2026-01-05 14:24:12 | D6: 13001002256309 | E6: Penerimaan Penjualan (AKR Corporindo) | F6: PT AKR CORPORINDO TBK-BANK PERMATA-INV 4 | G6: Kredit | H6: 0 | I6: 117154200 | J6: 2.1576922e+08 | K6: BRI0372 | L6: 563
A7: 3 | B7: 2026-01 | C7: 2026-01-05 16:15:26 | D7: 13001002256309 | E7: Transfer Keluar BI-Fast / Bank Transfer | F7: ESB:INDS:0002A00W:0c53613fe6cb | G7: Debet | H7: 97000000 | I7: 0 | J7: 1.1876922e+08 | K7: 0130055 | L7: 2
A8: 4 | B8: 2026-01 | C8: 2026-01-05 18:03:16 | D8: 13001002256309 | E8: Transfer Keluar BI-Fast / Bank Transfer | F8: ATMSTRPRM 08888 000598445 1140006499076 | G8: Debet | H8: 100000000 | I8: 0 | J8: 18769221 | K8: 8890407 | L8: 2
A9: 5 | B9: 2026-01 | C9: 2026-01-05 18:03:16 | D9: 13001002256309 | E9: Biaya Admin Bank & Transfer | F9: ATMSTRPRM 08888 000598445 1140006499076 | G9: Debet | H9: 6500 | I9: 0 | J9: 18762721 | K9: 8890407 | L9: 2
A10: 6 | B10: 2026-01 | C10: 2026-01-05 18:06:12 | D10: 13001002256309 | E10: Transfer Keluar BI-Fast / Bank Transfer | F10: ATMSTRPRM 08888 000628332 1140010073537 | G10: Debet | H10: 17000000 | I10: 0 | J10: 1762721.5 | K10: 8890405 | L10: 2
A11: 7 | B11: 2026-01 | C11: 2026-01-05 18:06:12 | D11: 13001002256309 | E11: Biaya Admin Bank & Transfer | F11: ATMSTRPRM 08888 000628332 1140010073537 | G11: Debet | H11: 6500 | I11: 0 | J11: 1756221.5 | K11: 8890405 | L11: 2
A12: 8 | B12: 2026-01 | C12: 2026-01-08 13:42:58 | D12: 13001002256309 | E12: Penerimaan Penjualan (AKR Corporindo) | F12: PT AKR CORPORINDO-BANK PERMATA-INV: 470 | G12: Kredit | H12: 0 | I12: 43461000 | J12: 45217221 | K12: BRI0372 | L12: 563
A13: 9 | B13: 2026-01 | C13: 2026-01-08 15:12:41 | D13: 13001002256309 | E13: Transfer Keluar BI-Fast / Bank Transfer | F13: ATMSTRPRM 08888 000936780 1140006499076 | G13: Debet | H13: 43000000 | I13: 0 | J13: 2217221.5 | K13: 8890405 | L13: 2
A14: 10 | B14: 2026-01 | C14: 2026-01-08 15:12:41 | D14: 13001002256309 | E14: Biaya Admin Bank & Transfer | F14: ATMSTRPRM 08888 000936780 1140006499076 | G14: Debet | H14: 6500 | I14: 0 | J14: 2210721.5 | K14: 8890405 | L14: 2
A15: 11 | B15: 2026-01 | C15: 2026-01-08 15:14:01 | D15: 13001002256309 | E15: Transfer Keluar BI-Fast / Bank Transfer | F15: ATMSTRPRM 08888 000959306 1140010073537 | G15: Debet | H15: 1000000 | I15: 0 | J15: 1210721.5 | K15: 8890409 | L15: 2
A16: 12 | B16: 2026-01 | C16: 2026-01-08 15:14:01 | D16: 13001002256309 | E16: Biaya Admin Bank & Transfer | F16: ATMSTRPRM 08888 000959306 1140010073537 | G16: Debet | H16: 6500 | I16: 0 | J16: 1204221.5 | K16: 8890409 | L16: 2
... A215: 211 | B215: 2026-07 | C215: 2026-07-30 14:23:04 | D215: 13001002256309 | E215: Penerimaan Penjualan (AKR Corporindo) | F215: PT AKR CORPORINDO-BANK PERMATA-INV 148 & | G215: Kredit | H215: 0 | I215: 33866800 | J215: 154976813 | K215: BRI0372 | L215: 563
B216: TOTAL | C216: - | D216: - | E216: - | F216: - | G216: - | H216: =SUM(H5:H215) -> 4.5272452e+09 | I216: =SUM(I5:I215) -> 4680849241 | J216: 154976813 | K216: - | L216: -

Sheet Rekap Bulanan
A1: REKAPITULASI DETAIL PER BULAN
A2: Breakdown Transaksi & Transaksi Terbesar Per Bulan
A4: Bulan | B4: Saldo Awal | C4: Total Uang Masuk | D4: Total Uang Keluar | E4: Net Cash Flow | F4: Saldo Akhir | G4: Jml Tran | H4: Transaksi Masuk Terbesar | I4: Nominal (Rp) | J4: Transaksi Keluar Terbesar | K4: Nominal (Rp)
A5: Januari 2026 | B5: 1372774.5 | C5: =SUMIFS('Detail Transaksi'!I:I, 'Detail Transaksi'!B:B, "2026-01") -> 473115365 | D5: =SUMIFS('Detail Transaksi'!H:H, 'Detail Transaksi'!B:B, "2026-01") -> 473341439 | E5: =C5-D5 -> -226074 | F5: 1146700.5 | G5: 34 | H5: PT AKR CORPORINDO TBK-BANK PERMATA-INV 4 | I5: 117154200 | J5: ATMSTRPRM 08888 000598445 1140006499076 | K5: 100000000
A6: Februari 2026 | B6: 1146700.5 | C6: =SUMIFS('Detail Transaksi'!I:I, 'Detail Transaksi'!B:B, "2026-02") -> 536517008 | D6: =SUMIFS('Detail Transaksi'!H:H, 'Detail Transaksi'!B:B, "2026-02") -> 536466203 | E6: =C6-D6 -> 50805 | F6: 1197505.5 | G6: 30 | H6: PT AKR CORPORINDO TBK-BANK PERMATA-INV 4 | I6: 201570700 | J6: ESB:INDS:0002A00W:b87ba2f455f0 | K6: 100000000
A7: Maret 2026 | B7: 1197505.5 | C7: =SUMIFS('Detail Transaksi'!I:I, 'Detail Transaksi'!B:B, "2026-03") -> 571817393 | D7: =SUMIFS('Detail Transaksi'!H:H, 'Detail Transaksi'!B:B, "2026-03") -> 572656281 | E7: =C7-D7 -> -838888 | F7: 358617.47 | G7: 35 | H7: PT. AKR CORPORINDO TBK.-BANK PERMATA-INV | I7: 131661000 | J7: ESB:INDS:0002A00W:61a705311d13 | K7: 150000000
A8: April 2026 | B8: 358617.47 | C8: =SUMIFS('Detail Transaksi'!I:I, 'Detail Transaksi'!B:B, "2026-04") -> 1976867276 | D8: =SUMIFS('Detail Transaksi'!H:H, 'Detail Transaksi'!B:B, "2026-04") -> 1.9670064e+09 | E8: =C8-D8 -> 9860865.5 | F8: 10219483 | G8: 35 | H8: PNCAIRN AN PT HIJAU SEJAHTERA DEPLESI | I8: 1500000000 | J8: SETORAN DEPLESI AN PT HIJAU SEJAHTERA | K8: 1500000000
A9: Mei 2026 | B9: 10219483 | C9: =SUMIFS('Detail Transaksi'!I:I, 'Detail Transaksi'!B:B, "2026-05") -> 157546791 | D9: =SUMIFS('Detail Transaksi'!H:H, 'Detail Transaksi'!B:B, "2026-05") -> 76518480 | E9: =C9-D9 -> 81028311 | F9: 91247794 | G9: 18 | H9: TUNAI ; ESB:INDS:0002800D:fefa14d6dc24 | I9: 55000000 | J9: ANG PJM AN PT HIJAU SEJAHTERA | K9: 51805000
A10: Juni 2026 | B10: 91247794 | C10: =SUMIFS('Detail Transaksi'!I:I, 'Detail Transaksi'!B:B, "2026-06") -> 475643583 | D10: =SUMIFS('Detail Transaksi'!H:H, 'Detail Transaksi'!B:B, "2026-06") -> 419689165 | E10: =C10-D10 -> 55954418 | F10: 147202212 | G10: 29 | H10: PT AKR COPORINDO TBK-BANK PERMATA-INV 07 | I10: 213928000 | J10: ATMSTRPRM 08888 000206430 1140016063946 | K10: 100000000
A11: Juli 2026 | B11: 147202212 | C11: =SUMIFS('Detail Transaksi'!I:I, 'Detail Transaksi'!B:B, "2026-07") -> 489341825 | D11: =SUMIFS('Detail Transaksi'!H:H, 'Detail Transaksi'!B:B, "2026-07") -> 481567224 | E11: =C11-D11 -> 7774601 | F11: 154976813 | G11: 30 | H11: PT AKR CORPORINDO TBK-BANK PERMATA-INV 1 | I11: 145563000 | J11: ATMSTRPRM 08888 000041165 1140010073537 | K11: 100000000

Sheet Payment Akr
A1: DETAIL TRANSFER MASUK - PT AKR CORPORINDO TBK
A2: No. Rekening: 13001002256309 | Periode: Januari - Juli 2026 | Rekap Penerimaan Penjualan AKR
A4: TOTAL PENERIMAAN AKR | C4: JUMLAH TRANSAKSI | E4: RATA-RATA PER TRANSAKSI | G4: TRANSAKSI TERBESAR
A5: =SUM(H8:H39) -> 2487698344 | C5: 32 | E5: =AVERAGE(H8:H39) -> 77740573 | G5: =MAX(H8:H39) -> 213928000
A7: No | B7: Periode | C7: Tanggal & Waktu | D7: No. Rekening | E7: Kategori | F7: Keterangan / Remark | G7: Jenis (GL) | H7: Mutasi Kredit / Masuk (Rp) | I7: User ID | J7: Kode Tran
A8: 1 | B8: 2026-01 | C8: 2026-01-05 13:54:10 | D8: 13001002256309 | E8: Penerimaan Penjualan (AKR Corporindo) | F8: PT AKR CORPORINDO-BANK PERMATA-INV 464,4 | G8: Kredit | H8: 97242247 | I8: BRI0372 | J8: 563
A9: 2 | B9: 2026-01 | C9: 2026-01-05 14:24:12 | D9: 13001002256309 | E9: Penerimaan Penjualan (AKR Corporindo) | F9: PT AKR CORPORINDO TBK-BANK PERMATA-INV 4 | G9: Kredit | H9: 117154200 | I9: BRI0372 | J9: 563
A10: 3 | B10: 2026-01 | C10: 2026-01-08 13:42:58 | D10: 13001002256309 | E10: Penerimaan Penjualan (AKR Corporindo) | F10: PT AKR CORPORINDO-BANK PERMATA-INV: 470 | G10: Kredit | H10: 43461000 | I10: BRI0372 | J10: 563
A11: 4 | B11: 2026-01 | C11: 2026-01-12 14:23:34 | D11: 13001002256309 | E11: Penerimaan Penjualan (AKR Corporindo) | F11: PT AKR CORPORINDO TBK-BANK PERMATA-INV 4 | G11: Kredit | H11: 109603000 | I11: BRI0372 | J11: 563
A12: 5 | B12: 2026-01 | C12: 2026-01-29 14:23:44 | D12: 13001002256309 | E12: Penerimaan Penjualan (AKR Corporindo) | F12: PT AKR CORPORINDO-BANK PERMATA-INV:478 & | G12: Kredit | H12: 53153200 | I12: BRI0372 | J12: 563
A13: 6 | B13: 2026-02 | C13: 2026-02-09 15:03:43 | D13: 13001002256309 | E13: Penerimaan Penjualan (AKR Corporindo) | F13: PT AKR CORPORINDO-BANK PERMATA-INV 004&0 | G13: Kredit | H13: 21589166 | I13: BRI0372 | J13: 563
A14: 7 | B14: 2026-02 | C14: 2026-02-09 15:03:45 | D14: 13001002256309 | E14: Penerimaan Penjualan (AKR Corporindo) | F14: PT AKR CORPORINDO TBK-BANK PERMATA-INV 4 | G14: Kredit | H14: 201570700 | I14: BRI0372 | J14: 563
A15: 8 | B15: 2026-02 | C15: 2026-02-12 13:42:57 | D15: 13001002256309 | E15: Penerimaan Penjualan (AKR Corporindo) | F15: PT AKR CORPORINDO-BANK PERMATA-INV: 481 | G15: Kredit | H15: 28457200 | I15: BRI0372 | J15: 563
A16: 9 | B16: 2026-02 | C16: 2026-02-19 13:52:54 | D16: 13001002256309 | E16: Penerimaan Penjualan (AKR Corporindo) | F16: PT AKR CORPORINDO TBK-BANK PERMATA-INV 0 | G16: Kredit | H16: 100089000 | I16: BRI0372 | J16: 563
A17: 10 | B17: 2026-02 | C17: 2026-02-19 14:43:02 | D17: 13001002256309 | E17: Penerimaan Penjualan (AKR Corporindo) | F17: PT AKR CORPORINDO TBK-BANK PERMATA-INV : | G17: Kredit | H17: 174810400 | I17: BRI0372 | J17: 563
A18: 11 | B18: 2026-03 | C18: 2026-03-02 14:24:38 | D18: 13001002256309 | E18: Penerimaan Penjualan (AKR Corporindo) | F18: PT AKR CORPORINDO TBK-BANK PERMATA-INV 0 | G18: Kredit | H18: 116833600 | I18: BRI0372 | J18: 563
A19: 12 | B19: 2026-03 | C19: 2026-03-02 14:54:00 | D19: 13001002256309 | E19: Penerimaan Penjualan (AKR Corporindo) | F19: PT. AKR CORPORINDO TBK.-BANK PERMATA-INV | G19: Kredit | H19: 131661000 | I19: BRI0372 | J19: 563
... A39: 32 | B39: 2026-07 | C39: 2026-07-30 14:23:04 | D39: 13001002256309 | E39: Penerimaan Penjualan (AKR Corporindo) | F39: PT AKR CORPORINDO-BANK PERMATA-INV 148 & | G39: Kredit | H39: 33866800 | I39: BRI0372 | J39: 563
B40: TOTAL AKR | C40: - | D40: - | E40: - | F40: - | G40: - | H40: =SUM(H8:H39) -> 2487698344 | I40: - | J40: -
